trajpandas/__init__.py
trajpandas/io/__init__.py
trajpandas/io/trm.py
trajpandas/synthetic.py
trajpandas/utils/__init__.py
trajpandas/utils/grid.py
trajpandas/utils/lldist.py
trajpandas-0.3.0.dist-info/LICENSE
trajpandas-0.3.0.dist-info/WHEEL
trajpandas-0.3.0.dist-info/METADATA
trajpandas-0.3.0.dist-info/RECORD
