Metadata-Version: 2.1
Name: trajpandas
Version: 0.3.0
Summary: 
Author: Bror Jonsson
Author-email: brorfred@gmail.com
Requires-Python: >=3.7
Classifier: Programming Language :: Python :: 3
Classifier: Programming Language :: Python :: 3.7
Classifier: Programming Language :: Python :: 3.8
Requires-Dist: numpy (>=1,<2)
Requires-Dist: pandas (>=1,<2)
Requires-Dist: scipy (>=1,<2)
